rcbench/__init__.py
rcbench/logger.py
rcbench/classes/Measurement.py
rcbench/classes/__init__.py
rcbench/classes/sample.py
rcbench/measurements/__init__.py
rcbench/measurements/dataset.py
rcbench/measurements/loader.py
rcbench/measurements/parser.py
rcbench/tasks/__init__.py
rcbench/tasks/baseevaluator.py
rcbench/tasks/featureselector.py
rcbench/tasks/generalizationrank.py
rcbench/tasks/ipc.py
rcbench/tasks/kernelrank.py
rcbench/tasks/memorycapacity.py
rcbench/tasks/narma.py
rcbench/tasks/nlt.py
rcbench/tasks/nonlinearmemory.py
rcbench/tasks/sinx.py
rcbench/utils/__init__.py
rcbench/utils/utils.py
rcbench/visualization/__init__.py
rcbench/visualization/base_plotter.py
rcbench/visualization/mc_plotter.py
rcbench/visualization/narma_plotter.py
rcbench/visualization/nlt_plotter.py
rcbench/visualization/plot_config.py
rcbench/visualization/sinx_plotter.py
rcbench-0.1.50.dist-info/licenses/LICENSE
rcbench-0.1.50.dist-info/METADATA
rcbench-0.1.50.dist-info/WHEEL
rcbench-0.1.50.dist-info/top_level.txt
rcbench-0.1.50.dist-info/RECORD
